dnd/__init__.py
dnd/api.py
dnd/bench.py
dnd/common.py
dnd/env.py
dnd/nvtools.py
dnd/reports.py
dnd/run.py
dnd/sample_app.py
dnd/tracer.py
dndlprof-0.10.0.dist-info/LICENSE
dndlprof-0.10.0.dist-info/METADATA
dndlprof-0.10.0.dist-info/WHEEL
dndlprof-0.10.0.dist-info/entry_points.txt
dndlprof-0.10.0.dist-info/top_level.txt
dndlprof-0.10.0.dist-info/RECORD
