Metadata-Version: 2.1
Name: dndlprof
Version: 0.10.0
Summary: A simple tool for profiling and tracing PyTorch programs on NVIDIA GPUs
Author: Michael Davies
Author-email: michaelstoby@gmail.com
License-File: LICENSE
Requires-Dist: numpy
Requires-Dist: pandas
Requires-Dist: torch
